{
  "hero": {
    "title": "",
    "date": "Feb 26 - 28, 2023",
    "dateLayout": false,
    "time": "Austin, TX",
    "buttons": {
      "registerButton": {
        "text": "Register Now",
        "display": true
      },
      "loginButton": {
        "text": "Log In",
        "display": false
      }
    },
    "images": [
      {
        "src": "yimbytown-keyimage-blue.png.png"
      }
    ],
    "background": {
      "src": "",
      "alt": ""
    }
  },
  "countdown": {
    "display": true,
    "text": "Y'all In Our Backyard"
  },
  "leftColumn": {
    "schedule": {
      "display": false,
      "title": "Full Event Schedule"
    },
    "disqus": {
      "title": "Join the Conversation"
    },
    "image": {
      "title": "Image"
    }
  },
  "masonry": [
    {
      "placement": "Top Left",
      "size": 2,
      "images": [
        {
          "src": "cherrywood_audience.jpg"
        },
        {
          "src": "bikeshare.jpeg"
        },
        {
          "src": "7ffed12b-9a1d-41a5-83c8-5c58a0dd1445.jpg"
        }
      ]
    },
    {
      "placement": "Top Right",
      "size": 1,
      "images": [
        {
          "src": "skyline-bluegray.jpeg"
        }
      ]
    },
    {
      "placement": "Bottom Left",
      "size": 1,
      "images": [
        {
          "src": "farm_city-logo-horizontal-cmyk.jpg"
        }
      ]
    },
    {
      "placement": "Bottom Right",
      "size": 2,
      "images": [
        {
          "src": "logotype-color.png"
        }
      ]
    }
  ]
}